mlgame3d/__init__.py
mlgame3d/__main__.py
mlgame3d/game_env.py
mlgame3d/game_runner.py
mlgame3d/mlplay.py
mlgame3d/mlplay_loader.py
mlgame3d/side_channel/__init__.py
mlgame3d/side_channel/game_parameters_side_channel.py
mlgame3d/side_channel/keyboard_state_side_channel.py
mlgame3d/side_channel/observation_structure_side_channel.py
mlgame3d/side_channel/player_control_side_channel.py
mlgame3d/side_channel/ranking_side_channel.py
mlgame3d-0.8.0.dist-info/licenses/LICENCE
mlgame3d-0.8.0.dist-info/METADATA
mlgame3d-0.8.0.dist-info/WHEEL
mlgame3d-0.8.0.dist-info/top_level.txt
mlgame3d-0.8.0.dist-info/RECORD
