Metadata-Version: 2.4
Name: mlgame3d
Version: 0.8.0
Summary: A framework for playing Unity games with Python agents using ML-Agents Environment.
Home-page: https://github.com/PAIA-Playful-AI-Arena/MLGame3D
Author: PAIA
Author-email: PAIA <service@paia-tech.com>
License: MIT
Project-URL: Homepage, https://github.com/PAIA-Playful-AI-Arena/MLGame3D
Project-URL: Repository, https://github.com/PAIA-Playful-AI-Arena/MLGame3D
Classifier: Programming Language :: Python :: 3.11
Classifier: License :: OSI Approved :: MIT License
Classifier: Operating System :: OS Independent
Requires-Python: >=3.11
License-File: LICENCE
Requires-Dist: mlgame3d-envs>=0.2.0
Requires-Dist: pandas
Dynamic: author
Dynamic: home-page
Dynamic: license-file
Dynamic: requires-python
